gs/__init__.py
gs/cli.py
gs/version.py
gs/packages/__init__.py
gs/packages/backports/__init__.py
gs/packages/backports/functools_lru_cache.py
gs/packages/backports/shutil_get_terminal_size.py
gs/packages/backports/tempfile.py
gs/packages/backports/weakref.py
gs/util/__init__.py
gs/util/compat.py
gs/util/exceptions.py
gs/util/printing.py
gs-1.1.1.dist-info/LICENSE
gs-1.1.1.dist-info/METADATA
gs-1.1.1.dist-info/WHEEL
gs-1.1.1.dist-info/entry_points.txt
gs-1.1.1.dist-info/top_level.txt
gs-1.1.1.dist-info/RECORD
