Metadata-Version: 2.1
Name: gs
Version: 1.1.1
Summary: A minimalistic Google Storage client
Home-page: https://github.com/kislyuk/gs
Author: Andrey Kislyuk
Author-email: kislyuk@gmail.com
License: MIT License
Platform: MacOS X
Platform: Posix
Classifier: Intended Audience :: Developers
Classifier: License :: OSI Approved :: MIT License
Classifier: Operating System :: MacOS :: MacOS X
Classifier: Operating System :: POSIX
Classifier: Programming Language :: Python
Classifier: Programming Language :: Python :: 3.6
Classifier: Programming Language :: Python :: 3.7
Classifier: Programming Language :: Python :: 3.8
Classifier: Programming Language :: Python :: 3.9
Classifier: Topic :: Software Development :: Libraries :: Python Modules
License-File: LICENSE
